minix/__init__.py
minix/core/__init__.py
minix/core/bootstrap/__init__.py
minix/core/bootstrap/bootstrap.py
minix/core/cli/__init__.py
minix/core/cli/cli.py
minix/core/connectors/__init__.py
minix/core/connectors/connector.py
minix/core/connectors/object_storage_connector/__init__.py
minix/core/connectors/object_storage_connector/config.py
minix/core/connectors/object_storage_connector/connector.py
minix/core/connectors/qdrant_connector/__init__.py
minix/core/connectors/qdrant_connector/connector.py
minix/core/connectors/sql_connector/__init__.py
minix/core/connectors/sql_connector/sql_connector.py
minix/core/consumer/__init__.py
minix/core/consumer/async_consumer.py
minix/core/controller/__init__.py
minix/core/controller/controller.py
minix/core/entity/__init__.py
minix/core/entity/entity.py
minix/core/entity/qdrant_entity.py
minix/core/entity/redis_entity.py
minix/core/entity/sql_entity.py
minix/core/install/__init__.py
minix/core/install/installable.py
minix/core/model/__init__.py
minix/core/model/embedding_model.py
minix/core/model/mlflow_model.py
minix/core/model/model.py
minix/core/model/model_registry.py
minix/core/module/__init__.py
minix/core/module/business_module/__init__.py
minix/core/module/business_module/business_module.py
minix/core/module/module.py
minix/core/object_storage/__init__.py
minix/core/object_storage/config.py
minix/core/object_storage/connector.py
minix/core/registry/__init__.py
minix/core/registry/registry.py
minix/core/repository/__init__.py
minix/core/repository/qdrant/__init__.py
minix/core/repository/qdrant/qdrant_repository.py
minix/core/repository/redis/__init__.py
minix/core/repository/redis/redis_repository.py
minix/core/repository/repository.py
minix/core/repository/sql/__init__.py
minix/core/repository/sql/sql_repository.py
minix/core/scheduler/__init__.py
minix/core/scheduler/scheduler.py
minix/core/scheduler/task/__init__.py
minix/core/scheduler/task/task.py
minix/core/service/__init__.py
minix-0.1.33.dist-info/METADATA
minix-0.1.33.dist-info/WHEEL
minix-0.1.33.dist-info/entry_points.txt
minix-0.1.33.dist-info/RECORD
