Metadata-Version: 2.4
Name: minix
Version: 0.1.33
Summary: A modular Python framework for backend, AI, and data projects
Author: AmirHossein Advari
Author-email: amiradvari@gmail.com
Requires-Python: >=3.10
Classifier: Programming Language :: Python :: 3
Classifier: Programming Language :: Python :: 3.10
Classifier: Programming Language :: Python :: 3.11
Classifier: Programming Language :: Python :: 3.12
Classifier: Programming Language :: Python :: 3.13
Classifier: Programming Language :: Python :: 3.14
Requires-Dist: aiokafka (>=0.12.0,<0.13.0)
Requires-Dist: boto3 (>=1.39.14,<2.0.0)
Requires-Dist: celery (>=5.5.3,<6.0.0)
Requires-Dist: celery-redbeat (>=2.3.2)
Requires-Dist: dotenv (>=0.9.9,<0.10.0)
Requires-Dist: fastapi (>=0.116.1,<0.117.0)
Requires-Dist: pymysql (>=1.1.1,<2.0.0)
Requires-Dist: redis (>=4.6.0,<5.0.0)
Requires-Dist: sqlalchemy (>=2.0.41,<3.0.0)
Requires-Dist: uvicorn (>=0.35.0,<0.36.0)
